{
    "features": [
        {
            "reference": "Abū ʿAbd Allãh al-Ḥimyarī (d. 900 AH). <i>Rawḍ al-miʿṭār fī ḫabar al-aqṭār</i>. Ed. by Iḥsān ʿAbbās. 2nd edition. Bayrūt, 1980",
            "source": "al-Ḥimyarī’s <i>Rawḍ al-miʿṭār</i>",
            "text": "<h1 class=\"arabic\">نخلة</h1>\n<p class=\"arabic\">موضع على ليلة من مكة.</p>\n<p class=\"arabic\">وكان بها لقريش وبني كنانة بعض الطواغيت التي كانت تعظمها مع الكعبة لأنهم قالوا ` اجعل الآلهة إلها واحدا ` الآية، فكانت لهم بيوت تعظمها وتطوف بها كطوافها بالكعبة، بعضها الذي بنخلة وكان سدنتها وحجابها من بني شيبان، وبها كانت العزى، فبعث إليها رسول الله صلى الله عليه وسلم خالد بن الوليد رضي الله عنه فلما سمع صاحبها ذلك علق عليها سيفه وأسند في الجبل الذي هو فيه، وانتهى إليها خالد رضي الله عنه فهدمها، ثم رجع إلى رسول الله صلى الله عليه وسلم.</p>",
            "title": "نخلة",
            "uri": "0900AbuCabdAllahHimyari.RawdMictar.Shamela0001043-ara1.001526-000.json"
        }
    ],
    "type": "FeatureCollection"
}