{
    "features": [
        {
            "reference": "Abū ʿAbd Allãh al-Ḥimyarī (d. 900 AH). <i>Rawḍ al-miʿṭār fī ḫabar al-aqṭār</i>. Ed. by Iḥsān ʿAbbās. 2nd edition. Bayrūt, 1980",
            "source": "al-Ḥimyarī’s <i>Rawḍ al-miʿṭār</i>",
            "text": "<h1 class=\"arabic\">العروض</h1>\n<p class=\"arabic\">بفتح أوله، اسم لمكة والمدينة معروف، يقول: استعمل فلان على العراق وفلان على العروض. وقالوا: خرج رسول الله صلى الله عليه وسلم يوم عاشوراء فأمرهم أن يؤذنوا أهل العروض أن يتموا بقية يومهم.</p>\n<p class=\"arabic\">والعروض أيضا موضع بالبادية.</p>",
            "title": "العروض",
            "uri": "0900AbuCabdAllahHimyari.RawdMictar.Shamela0001043-ara1.001045-000.json"
        }
    ],
    "type": "FeatureCollection"
}