{
    "features": [
        {
            "item": "JK_000129_011805",
            "properties": {
                "reference": "Yāqūt al-Ḥamawī. <i>Muʿjam al-buldān</i>. (5 vols.) Bayrūt: Dār Ṣādir, 1977, Vol.5, p.101",
                "source": "معجم البلدان لياقوت",
                "text": "<h1>مرج الصفر</h1> بالضم وتشديد الفاء بدمشق ذكر أيضا قال شهدت قبائل مالك وتغيبت عني عميرة يوم مرج الصفر وقال خالد بن سعيد بن العاصي وقتل بمرج الصفر هل فارس كره النزال يعيرني رمحا إذا نزلوا بمرج الصفر ",
                "title": "مرج الصفر",
                "uri": "JK_000129_011805"
            },
            "type": "Feature"
        }
    ],
    "type": "FeatureCollection"
}