{
    "features": [
        {
            "item": "JK_000129_007685",
            "properties": {
                "reference": "Yāqūt al-Ḥamawī. <i>Muʿjam al-buldān</i>. (5 vols.) Bayrūt: Dār Ṣādir, 1977, Vol.3, pp.364-365",
                "source": "معجم البلدان لياقوت",
                "text": "<h1>شمنصير</h1> بفتحتين ثم نون ساكنة وصاد مهملة مكسورة ثم ياء آخر الحروف ساكنة وراء اسم جبل في بلاد هذيل وقرأت بخط ابن جني في كتاب هذا لفظه قال شمنصير جبل بساية و ساية واد عظيم به أكثر من سبعين عينا وهو وادي أمج وقال ساعدة بن جؤية الهذلي أخيل برقا متى جاب له زجل إذا تغير عن توماضه جلجا مستأرضا بين بطن الليث أيمنه إلى شمنصير غيثا مرسلا معجا أخيل برقا أي أرى ومتى جاب أي متى جانب وجاب سحاب متراكب وقال أبو صخر الهذلي يرثي ولده تليدا وذكرني بكاي على تليد حمامة مر جاوبت الحماما ترجع منطقا عجبا وأوفت كنائحة أتت نوحا قياما تنادي ساق حر ظلت أدعو تليدا لا تبين به الكلاما لعلك هالك إما غلام تبوأ من شمنصير مقاما يخاطب نفسه وهو أحد فوائت كتاب سيبويه قال ابن جني يجوز أن يكون مأخوذا من شمصر لضرورة الوزن إن كان عربيا وقال الأزهري يقال شمصرت عليه إذا ضيقت عليه وقال عرام يتصل بضرعاء وهي قرية قرب ذرة من أرة شمنصير وهو جبل ململم لم يعله قط أحد ولا درى ما على ذروته فأعلاه القرود والمياه حواليه تحول ينابيع تطيف به قرية رهاط بوادي غران |جـ 3 صـ 365| ويقال إن أكثر نباته النبع والشوحط وينبت عليه النخل والحمص ",
                "title": "شمنصير",
                "uri": "JK_000129_007685"
            },
            "type": "Feature"
        }
    ],
    "type": "FeatureCollection"
}