{
    "features": [
        {
            "item": "JK_000129_010935",
            "properties": {
                "reference": "Yāqūt al-Ḥamawī. <i>Muʿjam al-buldān</i>. (5 vols.) Bayrūt: Dār Ṣādir, 1977, Vol.4, p.463",
                "source": "معجم البلدان لياقوت",
                "text": "<h1>كشكينان</h1> قال السلفي أبو عبد الله محمد بن عبد الله بن عبد البر القنباني المعروف بالكشكيناني نسب إلى قرية كشكينان من قنبانية قرطبة كان من الثقات في الرواية المجودين في الفتاوى وله حظوة عند الخليفة المستنصر أحد خلفاء بني أمية بالأندلس وقد دخل الشرق وكتب عنه عبد الرحمن بن عمر بن النحاس عن عبد الله بن يحيى الليثي ومحمد بن عبد الله بن عبد البر ابن عبد الأعلى بن سالم بن غيلان بن أبي مرزوق التجيبي المعروف بالكشكيناني من أهل قرطبة رحل إلى المشرق وسمع بمكة ومصر وانصرف إلى الأندلس وسمع منه الناس كثيرا ثم رحل ثانيا فحج وسمع ابن الأعرابي ومات بطرابلس الشام في سنة 141 ",
                "title": "كشكينان",
                "uri": "JK_000129_010935"
            },
            "type": "Feature"
        }
    ],
    "type": "FeatureCollection"
}