{
    "features": [
        {
            "item": "JK_000952_0503",
            "properties": {
                "reference": "al-Samʿānī. <i>Kitāb al-ansāb</i>. (5 vols.) Bayrūt: Dār al-fikr, 1998, Vol.1, pp.352-354",
                "source": "الأنساب للسمعاني",
                "text": "<h1>البسكايري</h1> بفتح الباء الموحدة وسكون السين المهملة وفتح الكاف والياء المكسورة المنقوطة باثنتين من تحتها وفي آخرها الراء هذه النسبة إلى بسكاير وهي قرية من قرى بخارا منها أبو المشهر أحمد بن علي بن طاهر بن محمد بن طاهر بن عبد الله بن طاهر بن ويرنك بن تازدار بن هرمز بن شهريار بن يزدجرد بن بهرام البسكايري من أهل هذه القرية كان فاضلا عالما عارفا بالأدب واللغة ورحل إلى خراسان والعراق والحجاز وأدرك |جـ 1 صـ 354| الشيوخ ورأيت له مجموعا بخطه بنسف حدث فيه عن جماعة من الشيوخ فاستحسنته جدا وكان يملي ببخارا سمع السيد أبا الحسن محمد بن علي الهمذاني وأبا سعيد الخليل بن أحمد السجزي وبترمذ أبا منصور الحسين بن علي بن يوسف الزاهد وبآمل أبا سعيد أحمد بن محمد بن فضلويه الآملي وبالدامغان أبا محمد الحسن بن محمد بن عتاب الخطيب وبسمنان أبا القاسم عبد الله بن عمر بن محمد بن الداية الكلوذاني وبالري أبا عبد الله الحسين بن جعفر الجرجاني الحافظ وببغداد أبا القاسم عبيد الله بن أحمد الصيدلاني وأبا الحسن محمد بن أحمد بن رزق البزاز وطبقتهم روى عنه أبو العباس جعفر بن محمد بن المعتز المستغفري وأبو محمد عبد العزيز بن محمد بن العاصمي وغيرهما وذكر العاصمي أن أبا المشهر كان يتكلم في بعض سماعه ولم تكن أصوله صحيحة ولم أكثر منه وأبو أحمد نبهان بن إسحاق بن مقداس الدهقان الفقيه الزاهد البسكايري سمع ببخارا من أبي عصمة سعد بن معاذ المروزي وسفيان بن عبد الحكم وأبي طاهر اسباط بن اليسع وأبي عبد الله بن أبي حفص ورحل إلى الشام ومصر وسمع ربيع بن سليمان المرادي وبكار بن قتيبة والعباس بن الوليد البيروتي وتوفي في المحرم سنة عشرين وثلاثمائة ",
                "title": "البسكايري",
                "uri": "JK_000952_0503"
            },
            "type": "Feature"
        }
    ],
    "type": "FeatureCollection"
}