{
    "features": [
        {
            "item": "JK_000129_003539",
            "properties": {
                "reference": "Yāqūt al-Ḥamawī. <i>Muʿjam al-buldān</i>. (5 vols.) Bayrūt: Dār Ṣādir, 1977, Vol.2, p.192",
                "source": "معجم البلدان لياقوت",
                "text": "<h1>جويك والنسبة الجويكي</h1> بالضم وكسر الواو وياء ساكنة وكاف محلة بنسف منها محمد بن حيدر بن الحسن الجويكي يروي عن محمد بن طالب وغيره ",
                "title": "جويك والنسبة الجويكي",
                "uri": "JK_000129_003539"
            },
            "type": "Feature"
        }
    ],
    "type": "FeatureCollection"
}