{
    "features": [
        {
            "item": "JK_000952_3873",
            "properties": {
                "reference": "al-Samʿānī. <i>Kitāb al-ansāb</i>. (5 vols.) Bayrūt: Dār al-fikr, 1998, Vol.5, p.343",
                "source": "الأنساب للسمعاني",
                "text": "<h1>المعشاري</h1> بكسر الميم وسكون العين المهملة وفتح الشين المعجمة والراء بعد الألف هذه النسبة إلى المعشار وهو بطن من همدان فيما أظن منها أبو الحسن محمد بن الحسن بن أبي يزيد الهمداني ثم المعشاري من أهل الكوفة قدم بغداد وحدث بها عن عمرو بن قيس الملائي وهشام بن عروة وجعفر بن محمد وعائذ المكتب وأبي حمزة الثمالي روى عنه سريج بن يونس ومحمد بن هشام المرو الروذي وشهاب بن عباد وحسين بن عبد الأول وعمرو بن زرارة وغيرهم وكان ضعيفا لينا في الحديث قال البخاري قال لي عمرو بن زرارة ثنا محمد بن الحسن أبو الحسن الهمداني نزل واسطا رأيته ببغداد عن عباد المنقري وسعيد بن عبد الرحمن وقال في موضع اخر ما أراه يسوي شيئا كان ينزل عند مقابر الخيزران جعل يحدثنا بأحاديث يجيء بها كما يحدث بها ابن أبي زائدة وأبو معاوية وقال أحمد بن حنبل هو ضعيف وقال يحيى بن معين هو ليس بثقة وقال أبو داود السجستاني هو كذاب وثب على كتب أبيه وقال أبو عبد الرحمن النسائي هو متروك الحديث ",
                "title": "المعشاري",
                "uri": "JK_000952_3873"
            },
            "type": "Feature"
        }
    ],
    "type": "FeatureCollection"
}