{
    "features": [
        {
            "item": "JK_000129_001624",
            "properties": {
                "reference": "Yāqūt al-Ḥamawī. <i>Muʿjam al-buldān</i>. (5 vols.) Bayrūt: Dār Ṣādir, 1977, Vol.1, pp.370-371",
                "source": "معجم البلدان لياقوت",
                "text": "<h1>بربشتر والنسبة البربشتري</h1> بضم الباء الثانية وسكون الشين المعجمة وفتح التاء المثناة من فوق مدينة عظيمة في شرقي الأندلس من أعمال بربطانية وقد صارت للروم في صدر سنة 254 حمل منها لصاحب القسطنطينية في جملة الهدايا سبعة آلاف بكر منتخبة ثم استعادها المسلمون في إمارة أحمد بن سليمان بن هود في سنة 75 بعد ذلك بخمسة أعوام فغنموا فيما غنموا عشرة آلاف امرأة ثم عادت إليهم خذلهم الله ولها |جـ 1 صـ 371| حصون كثيرة منها حصن القصر وحصن الباكة وحصن قصر مينوقش وغير ذلك وينسب إليها خلف بن يوسف المقري البربشتري أبو القاسم روى عن أبي عمرو المقري وأجاز له وكان من أهل القرآن والحديث والبراعة والفهم وتوفي في شهر رمضان سنة 154 ويوسف بن عمر بن أيوب بن زكرياء التجيبي الثغري البريشتري أبو عمرو وله رحلة سمع فيها بمصر من الحسن بن رشيق وغيره وكان يسكن الإسكندرية وبها حدث وسمع من أبي صخر بمكة قاله السلفي ",
                "title": "بربشتر والنسبة البربشتري",
                "uri": "JK_000129_001624"
            },
            "type": "Feature"
        }
    ],
    "type": "FeatureCollection"
}