{
    "features": [
        {
            "item": "JK_000129_008116",
            "properties": {
                "reference": "Yāqūt al-Ḥamawī. <i>Muʿjam al-buldān</i>. (5 vols.) Bayrūt: Dār Ṣādir, 1977, Vol.3, p.433",
                "source": "معجم البلدان لياقوت",
                "text": "<h1>صوران</h1> بالفتح ثم التشديد علم مرتجل اسم كورة بحمص وجبل وقيل موضع دون دابق في طرف الريف ذكره صخر الغي الهذلي في قوله مآبه الروم أو تنوخ أو ال آطام من صوران أو زبد ",
                "title": "صوران",
                "uri": "JK_000129_008116"
            },
            "type": "Feature"
        }
    ],
    "type": "FeatureCollection"
}