{
    "features": [
        {
            "item": "JK_000129_003904",
            "properties": {
                "reference": "Yāqūt al-Ḥamawī. <i>Muʿjam al-buldān</i>. (5 vols.) Bayrūt: Dār Ṣādir, 1977, Vol.2, p.252",
                "source": "معجم البلدان لياقوت",
                "text": "<h1>الحزامون</h1> بالفتح والتشديد محلة في شرقي واسط واسعة كبيرة لها ذكر في التواريخ كثير كأنها منسوبة إلى الذين يحزمون الأمتعة أي يشدونها والله أعلم وبالحزامين مشهد عليه قبة عالية يزعمون أن بها قبر محمد بن إبراهيم بن الحسن بن الحسن بن علي بن أبي طالب رضي الله عنهم وهناك قبر يزعمون أنه قبر عزرة بن هارون بن عمران يزوره المسلمون واليهود ",
                "title": "الحزامون",
                "uri": "JK_000129_003904"
            },
            "type": "Feature"
        }
    ],
    "type": "FeatureCollection"
}