{
    "features": [
        {
            "item": "JK_000952_2295",
            "properties": {
                "reference": "al-Samʿānī. <i>Kitāb al-ansāb</i>. (5 vols.) Bayrūt: Dār al-fikr, 1998, Vol.3, pp.395-396",
                "source": "الأنساب للسمعاني",
                "text": "<h1>الشبامي</h1> بكسر الشين المعجمة وفتح الباء الموحدة وفي آخرها الميم بعد الألف هذه النسبة إلى شبام وهي مدينة باليمن والمشهور بهذه النسبة عبد الجبار بن العباس الشبامي الهمداني من أهل الكوفة يروي عن عون بن أبي جحيفة وعطاء بن السائب روى عنه ابن أبي زائدة والكوفيون وكان ممن ينفرد بالمقلوبات عن الثقات وكان غاليا في التشيع وكان أبو نعيم يقول لم يكن بالكوفة أكذب من عبد الجبار بن العباس وأبي إسرائيل وإبراهيم بن سويد الشبامي يروي عن عبد الرزاق بن همام الصنعاني روى عنه أبو |جـ 3 صـ 396| القاسم سلميان بن أحمد بن أيوب الطبراني وذكر أنه سمع منه بمدينة شبام باليمن وحكي عن الطبراني أنه قال كنت مريضا في بعض يبعض الحوانيت بمدينة شبام فسمعت واحدا يقرأ هذه الآية إن عليا جمعه وقرأ به فإذا قرأناه فاتبع قراءته وأهلها كانوا من غلاة الشيعة فأردت أن أرد عليه فمنعني بعض الغرباء عن ذلك وقال أهل هذه المدينة كلها روافض لو قلت شيئا لسعيت في إراقة دمك الزم السكوت وسوار الشبامي ذكره ابن أبي حاتم في الجرح والتعديل وقال روى عنه مروان بن معاوية الفزاري سألت أبي عنه فقال لا أدري من هو ",
                "title": "الشبامي",
                "uri": "JK_000952_2295"
            },
            "type": "Feature"
        }
    ],
    "type": "FeatureCollection"
}