{
    "features": [
        {
            "item": "JK_000952_1774",
            "properties": {
                "reference": "al-Samʿānī. <i>Kitāb al-ansāb</i>. (5 vols.) Bayrūt: Dār al-fikr, 1998, Vol.3, p.58",
                "source": "الأنساب للسمعاني",
                "text": "<h1>الرزامي</h1> بكسر الراء وفتح الزاي وفي آخرها الميم هذه النسبة إلى محلة بمرو يقال لها حوض رزام وإلى الساعة المحلة بهذا الاسم تعرف وهذه المحلة منسوبة إلى رزام بن أبي رزام المطوعي الرزامي غزا مع عبد الله بن المبارك واستشهد قبل موت ابن المبارك بسنين وكان حوض رزام قبل ذلك مزارع فاتخذ رزام بها الحوض والمسجد والرزامية جماعة من غلاة الشيعة وهم طائفة من الروندية الذين ساقوا الإمامة من علي إلى محمد بن الحنفية ثم إلى ابنه ثم إلى علي بن عبد الله بن العباس بالوصية ثم ساقوها في ولده إلى المنصور ثم افترق هؤلاء في أبي مسلم فمنهم من قال إنه لم يقتل وادعوا حلول روح الإله فيه واستحلوا المحرم والمحرمات ومنهم كان المقنع ثم ادعى لنفسه الإلهية بكش ونخشب وعلى دينه اليوم مبيضة ما وراء النهر بإيلاق ",
                "title": "الرزامي",
                "uri": "JK_000952_1774"
            },
            "type": "Feature"
        }
    ],
    "type": "FeatureCollection"
}