{
    "features": [
        {
            "item": "JK_000952_4214",
            "properties": {
                "reference": "al-Samʿānī. <i>Kitāb al-ansāb</i>. (5 vols.) Bayrūt: Dār al-fikr, 1998, Vol.5, p.547",
                "source": "الأنساب للسمعاني",
                "text": "<h1>النهمي</h1> بضم النون وسكون الهاء وفي اخرها الميم هذه النسبة إلى بطن من بجيلة وهو عبد نهم بن مالك بن غانم بن مالك بن هوازن بن عرينة بن نذير بن قسر بن عبقر قاله ابن حبيب وفي قضاعة عبد نهم ومن ولده قيس بن رفاعة بن عبد نهم بن شحب بن مرة بن زري بن مالك بن نهد بن زيد بن ليث بن سود بن أسلم بن الحاف بن قضاعة الشاعر وكان فارسا قال ذلك ابن حبيب عن ابن الكلبي ",
                "title": "النهمي",
                "uri": "JK_000952_4214"
            },
            "type": "Feature"
        }
    ],
    "type": "FeatureCollection"
}