{
    "features": [
        {
            "item": "JK_000129_012051",
            "properties": {
                "reference": "Yāqūt al-Ḥamawī. <i>Muʿjam al-buldān</i>. (5 vols.) Bayrūt: Dār Ṣādir, 1977, Vol.5, p.146",
                "source": "معجم البلدان لياقوت",
                "text": "<h1>المضمار</h1> حصن من حصون اليمن لحمير على ميل ونصف من صنعاء حيث يجري الخيل ذكره في حديث العنسي ",
                "title": "المضمار",
                "uri": "JK_000129_012051"
            },
            "type": "Feature"
        }
    ],
    "type": "FeatureCollection"
}