{
    "features": [
        {
            "item": "JK_000129_009334",
            "properties": {
                "reference": "Yāqūt al-Ḥamawī. <i>Muʿjam al-buldān</i>. (5 vols.) Bayrūt: Dār Ṣādir, 1977, Vol.4, pp.187-188",
                "source": "معجم البلدان لياقوت",
                "text": "<h1>غدر</h1> بفتح أوله وسكون ثانيه وآخره راء بلفظ الغدر ضد الوفاء من قرى الأنبار الله تبارك وتعالى رضي الله عنهن الرب عز وجل |جـ 4 صـ 188| غدر بوزن زفر يجوز أن يكون معدولا من غادر من مخاليف اليمن وفيه ناعط ويذكر في موضعه وهو حصن عجيب وهو الكثير الحجارة الصعب المسلك وهو من البناء القديم ويصحف بعذر ",
                "title": "غدر",
                "uri": "JK_000129_009334"
            },
            "type": "Feature"
        }
    ],
    "type": "FeatureCollection"
}