{
    "features": [
        {
            "item": "JK_000952_2611",
            "properties": {
                "reference": "al-Samʿānī. <i>Kitāb al-ansāb</i>. (5 vols.) Bayrūt: Dār al-fikr, 1998, Vol.4, p.79",
                "source": "الأنساب للسمعاني",
                "text": "<h1>الطوريني</h1> بضم الطاء المهملة والراء المكسورة بينهما الواو ثم الياء الساكنة آخر الحروف وفي آخرها النون هذه النسبة إلى طورين وهي قرية من قرى الري على نصف فرسخ منها دخلتها وسمعت بها منها محمد بن سلمة بن مالك الرازي الباهلي الطوريني كان يسكن طورين يروي عن عبد العزيز بن أبي حازم وعبد العزيز الدراوردي وحاتم بن إسماعيل وفضيل بن عياض وعبد العزيز بن عبد الصمد وعبد الله بن رجاء المكي قال ابن أبي حاتم الرازي سألت أبي عنه فقال صدوق ما علمته إلا صحيح الحديث ",
                "title": "الطوريني",
                "uri": "JK_000952_2611"
            },
            "type": "Feature"
        }
    ],
    "type": "FeatureCollection"
}