{
    "features": [
        {
            "item": "JK_000952_2358",
            "properties": {
                "reference": "al-Samʿānī. <i>Kitāb al-ansāb</i>. (5 vols.) Bayrūt: Dār al-fikr, 1998, Vol.3, p.444",
                "source": "الأنساب للسمعاني",
                "text": "<h1>الشقري</h1> مثل الأول غير أن هذا بكسر القاف ينسب إلى شقرة وهو لقب معاوية بن الحارث بن تميم ومن يكون من ولده يقال له الشقري نسبة إليه وإنما لقب بالشقرة لقوله % وقد أحمل الرمح الأصم كعوبه % % به من دماء القوم كالشقرات % وهو أبو حي من تميم والشقر هو شقائق النعمان قاله أبو الحسن الدارقطني ",
                "title": "الشقري",
                "uri": "JK_000952_2358"
            },
            "type": "Feature"
        }
    ],
    "type": "FeatureCollection"
}