{
    "features": [
        {
            "item": "JK_000129_003353",
            "properties": {
                "reference": "Yāqūt al-Ḥamawī. <i>Muʿjam al-buldān</i>. (5 vols.) Bayrūt: Dār Ṣādir, 1977, Vol.2, p.162",
                "source": "معجم البلدان لياقوت",
                "text": "<h1>جمران</h1> بالضم ثم السكون كأنه مرتجل قيل هو جبل بحمى ضرية قال ربيعة أمن آل هند عرفت الرسوما بجمران قفرا أبت أن تريما وقال مالك بن الريب المازني علي دماء البدن إن لم تفارقي أبا حردب يوما وأصحاب حردب سرت في دجى ليل فأصبح دونها مفاوز جمران الشريف فغرب تطالع من وادي الكلاب كأنها وقد أنجدت منه فريدة ربرب وقال نصر جمران جبل أسود بين اليمامة وفيد من ديار تميم أو نمير بن عامر وقال أبو زياد جمران جبل مرت به بنو حنيفة منهزمين يوم النشناش في وقعة كانت بينهم وبين بني عقيل فقال شاعرهم ولو سئلت عنا حنيفة أخبرت بما لقيت منا بجمران صيدها ",
                "title": "جمران",
                "uri": "JK_000129_003353"
            },
            "type": "Feature"
        }
    ],
    "type": "FeatureCollection"
}