{
    "features": [
        {
            "item": "JK_000952_4174",
            "properties": {
                "reference": "al-Samʿānī. <i>Kitāb al-ansāb</i>. (5 vols.) Bayrūt: Dār al-fikr, 1998, Vol.5, pp.527-528",
                "source": "الأنساب للسمعاني",
                "text": "<h1>النميري</h1> بضم النون وفتح الميم وسكون الياء المنقوطة باثنتين من تحتها وفي اخرها راء هذه النسبة إلى بني نمير وهو نمير بن عامر بن صعصعة والمشهور بالنسبة إليها إياس بن قتادة العبشمي النميري ابن أخت الأحنف بن قيس من أهل البصرة كان على قضاء الري يروي عن قيس بن عباد روى عنه شعبة مات في أيام مصعب بن الزبير سنة إحدى وسبعين وأبو نافع صخر بن جويرية الأزدي النميري مولى بني نمير من أهل البصرة يروي عن نافع روى عنه ابن المبارك ويحيى القطان وأبو سليمان فضل بن سليمان النميري من أهل البصرة يروي عن أبي حازم وموسى بن عقبة روى عنه أهل البصرة مات سنة ست وثمانين ومئة وزياد بن عبد الله النميري شيخ من أهل البصرة يروي عن أنس بن مالك رضي الله عنه روى عنه أهل البصرة منكر الحديث يروي عن أنس بن مالك رضي الله عنه أشياء |جـ 5 صـ 528| لا تشبه حديث الثقات لايجوز الاحتجاج به تركه يحيى بن معين وعبد الله بن عمير النميري يقال إنه عبد الله بن غانم نزل إفريقية وهو الذي كان يكتب إلى مالك بن أنس في المسائل قال أبو علي الغساني هكذا روينا في نسبه النميري وقال عبد الغني فيه النمري بحذف ياء التصغير يروي عن يونس بن يزيد الأيلي روى عن حجاج بن محمد وأبو الفضل عصمة بن الفضل النميري سكن بغداد سمع حرمي بن عمارة بن أبي حفصة ومحمد بن بشر العبدي ويحيى بن ادم والحسين بن علي الجعفي وعبد الله بن الوليد العدني روى عنه أبو حاتم محمد بن إدريس الرازي والحسن بن علي بن شبيب المعمري ومحمد بن إسحاق بن خزيمة ومات سنة خمسين ومئتين ",
                "title": "النميري",
                "uri": "JK_000952_4174"
            },
            "type": "Feature"
        }
    ],
    "type": "FeatureCollection"
}