{
    "features": [
        {
            "item": "JK_000129_006096",
            "properties": {
                "reference": "Yāqūt al-Ḥamawī. <i>Muʿjam al-buldān</i>. (5 vols.) Bayrūt: Dār Ṣādir, 1977, Vol.3, pp.110-111",
                "source": "معجم البلدان لياقوت",
                "text": "<h1>الريان</h1> جبل في طريق البصرة |جـ 3 صـ 111| إلى مكة ",
                "title": "الريان",
                "uri": "JK_000129_006096"
            },
            "type": "Feature"
        }
    ],
    "type": "FeatureCollection"
}