{
    "features": [
        {
            "item": "JK_000952_4376",
            "properties": {
                "reference": "al-Samʿānī. <i>Kitāb al-ansāb</i>. (5 vols.) Bayrūt: Dār al-fikr, 1998, Vol.5, p.647",
                "source": "الأنساب للسمعاني",
                "text": "<h1>الهماني</h1> بضم الهاء وفتح الميم المخففة وفي اخرها النون هذه النسبة إلى همان وظني أنها قرية بالعراق من سواد بغداد والمشهور بهذه النسبة أبو الفرج الحسن بن أحمد بن علي الهماني من أهل بغداد روى عن عبد الله بن محمد بن جعفر بن شاذان وغيره روى عنه أبو القاسم عبد العزيز بن علي الأزجي وأبو الحسن أحمد بن محمد العتيقي وأبو الحسين محمد بن علي بن المهتدي بالله وغيرهم وأبو عمرو أحمد بن محمد بن الضحاك الهماني يروي عن عمار بن خالد روى عنه أبو بكر محمد بن إبراهيم بن المقرىء وقال حدثنا أحمد بن محمد بن الضحاك الهماني بها أبو عمرو ",
                "title": "الهماني",
                "uri": "JK_000952_4376"
            },
            "type": "Feature"
        }
    ],
    "type": "FeatureCollection"
}