{
    "features": [
        {
            "item": "JK_000952_0963",
            "properties": {
                "reference": "al-Samʿānī. <i>Kitāb al-ansāb</i>. (5 vols.) Bayrūt: Dār al-fikr, 1998, Vol.2, p.101",
                "source": "الأنساب للسمعاني",
                "text": "<h1>الجوادي</h1> بفتح الجيم والواو المشددة بعدهما الألف وفي آخرها الدال المهملة هذه النسبة إلى جواد وهو بطن من حضرموت خبيئة وجواد ابنا أثير بن جواد بن وديعة بن سلخب الأكبر من حضرموت ذكر ذلك ابن حبيب في نسب حضرموت ",
                "title": "الجوادي",
                "uri": "JK_000952_0963"
            },
            "type": "Feature"
        }
    ],
    "type": "FeatureCollection"
}