{
    "features": [
        {
            "item": "JK_000129_000308",
            "properties": {
                "reference": "Yāqūt al-Ḥamawī. <i>Muʿjam al-buldān</i>. (5 vols.) Bayrūt: Dār Ṣādir, 1977, Vol.1, p.117",
                "source": "معجم البلدان لياقوت",
                "text": "<h1>الأحمر</h1> حصن بظاهر بحر الشام وكان يعرف بعثليث ",
                "title": "الأحمر",
                "uri": "JK_000129_000308"
            },
            "type": "Feature"
        }
    ],
    "type": "FeatureCollection"
}