{
    "features": [
        {
            "item": "JK_000129_004780",
            "properties": {
                "reference": "Yāqūt al-Ḥamawī. <i>Muʿjam al-buldān</i>. (5 vols.) Bayrūt: Dār Ṣādir, 1977, Vol.2, pp.390-391",
                "source": "معجم البلدان لياقوت",
                "text": "<h1>خناصرة والنسبة الخناصري</h1> بليدة من أعمال حلب تحاذي قنسرين نحو البادية وهي قصبة كورة الأحص التي ذكرها الجعدي فقال فقال تجاوزت الأحص وماءه وقد ذكرها عدي بن الرقاع فقال وإذا الربيع تتابعت أنواؤه فسقى خناصرة الأحص وزادها قيل بناها خناصرة بن عمرو بن الحارث بن كعب ابن عمرو بن عبد ود بن عوف بن كنانة ملك الشام كذا ذكره ابن الكلبي وقال غيره عمرها الخناصر ابن عمرو خليفة الأشرم صاحب الفيل وينسب إليها أبو يزيد بن خالد بن محمد بن هاني الخناصري الأسدي حدث بحلب عن المسيب بن واضح روى عنه أبو بكر محمد بن الحسين بن صالح السبيعي نزيل حلب وذكرها المتنبي فقال أحب حمصا إلى خناصرة وكل نفس تحب محياها حيث التقى خدها وتفاح لب نان وثغري على حمياها وصفت فيها مصيف بادية شتوت بالحصحصان مشتاها إن أعشبت روضة رعيناها أو ذكرت حلة غزوناها وقال جران العود وجعلها خناصرات كأنه جعل |جـ 2 صـ 391| كل موضع منها خناصرة فقال نظرت وصحبتي بخناصرات ضحيا بعدما متع النهار إلى ظعن لأخت بني نمير بكابة حيث زاحمها العقار العقار الرمل ",
                "title": "خناصرة والنسبة الخناصري",
                "uri": "JK_000129_004780"
            },
            "type": "Feature"
        }
    ],
    "type": "FeatureCollection"
}