{
    "features": [
        {
            "item": "JK_000129_006251",
            "properties": {
                "reference": "Yāqūt al-Ḥamawī. <i>Muʿjam al-buldān</i>. (5 vols.) Bayrūt: Dār Ṣādir, 1977, Vol.3, p.137",
                "source": "معجم البلدان لياقوت",
                "text": "<h1>الزرقاء</h1> بلفظ تأنيث الأزرق موضع بالشام بناحية معان وهو نهر عظيم في شعارى ودحال كثيرة وهي أرض شيب التبعي الحميري وفيه سباع كثيرة مذكورة بالضراوة وهو نهر يصب في الغور ",
                "title": "الزرقاء",
                "uri": "JK_000129_006251"
            },
            "type": "Feature"
        }
    ],
    "type": "FeatureCollection"
}