{
    "features": [
        {
            "item": "JK_000129_009249",
            "properties": {
                "reference": "Yāqūt al-Ḥamawī. <i>Muʿjam al-buldān</i>. (5 vols.) Bayrūt: Dār Ṣādir, 1977, Vol.4, p.174",
                "source": "معجم البلدان لياقوت",
                "text": "<h1>عينم</h1> في وزن الذي قبله أراه منقولا من الفعل الماضي من العنم وهو ضرب من شجر الشوك لين الأغصان لطيفها كأنه بنان العذارى واحدتها عنمة والعنم ضرب من الوزغ يشبه العظاية إلا أنه أحسن منها وأشد بياضا وقيل العنم شجرة لها ثمر أحمر كالعناب تكون بالحجاز يشبه بها بنان النساء سمي بذلك لكثرته فيه أو يكون اسما غير عن صيغته فرقا بين الموضع وما فيه ",
                "title": "عينم",
                "uri": "JK_000129_009249"
            },
            "type": "Feature"
        }
    ],
    "type": "FeatureCollection"
}