{
    "features": [
        {
            "item": "JK_000129_006556",
            "properties": {
                "reference": "Yāqūt al-Ḥamawī. <i>Muʿjam al-buldān</i>. (5 vols.) Bayrūt: Dār Ṣādir, 1977, Vol.3, p.187",
                "source": "معجم البلدان لياقوت",
                "text": "<h1>سبيع</h1> تصغير سبع وقال نصر واد بنجد في قول عدي بن الرقاع العاملي كأنها وهي تحت الرحل لاهية إذا المطي على أنقابه ذملا جونية من قطا الصوان مسكنها جفاجف تنبت القعفاء والنقلا باضت بجزم سبيع أو بمرفضه ذي الشيح حيث تلاقى التلع فانسحلا سبيع موضع ومرفضه حيث انقطع الوادي وإياها فيما أحسب عنى الراعي بقوله كأني بصحراء السبيعين لم أكن بأمثال هند قبل هند مفجعا ",
                "title": "سبيع",
                "uri": "JK_000129_006556"
            },
            "type": "Feature"
        }
    ],
    "type": "FeatureCollection"
}