{
    "features": [
        {
            "item": "JK_000129_003398",
            "properties": {
                "reference": "Yāqūt al-Ḥamawī. <i>Muʿjam al-buldān</i>. (5 vols.) Bayrūt: Dār Ṣādir, 1977, Vol.2, pp.168-169",
                "source": "معجم البلدان لياقوت",
                "text": "<h1>جند والنسبة الجندي</h1> بالفتح ثم السكون ودال مهملة اسم مدينة عظيمة في بلاد تركستان بينها وبين خوارزم عشرة أيام تلقاء بلاد الترك مما وراء النهر قريب من نهر سيحون وأهلها مسلمون ينتحلون مذهب أبي حنيفة وهي الآن بيد التتر لعنهم الله لا يعرف حالها وإليها ينسب القاضي الأديب العالم الشاعر المنشىء النحوي يعقوب بن شيرين الجندي كان من أجل من قرأ على أبي القاسم الزمخشري وأقام بخوارزم |جـ 2 صـ 169| وقد ذكرته في كتاب النحويين ",
                "title": "جند والنسبة الجندي",
                "uri": "JK_000129_003398"
            },
            "type": "Feature"
        }
    ],
    "type": "FeatureCollection"
}