{
    "features": [
        {
            "item": "JK_000952_2387",
            "properties": {
                "reference": "al-Samʿānī. <i>Kitāb al-ansāb</i>. (5 vols.) Bayrūt: Dār al-fikr, 1998, Vol.3, pp.459-460",
                "source": "الأنساب للسمعاني",
                "text": "<h1>الشميهني</h1> بفتح الشين المعجمة وكسر الميم وسكون الياء المنقوطة باثنتين من تحتها وبعدها الهاء وفي آخرها النون هذه النسبة إلى شميهن وهي قرية من قرى مرو على فرسخين منها بأسفل نهر الأسقبذي والمشهور بالنسبة إليها محمد بن عبد الله بن قهزاذ الشميهني إمام متقن يروي عن النضر بن شميل وعبدان ويزيد بن أبي حكيم والحسن بن بشر وجماعة روى عنه مسلم بن الحجاج القشيري في صحيحه ومات يوم الأربعاء لعشر خلون من المحرم سنة اثنتين وستين ومائتين وأبو بكر عبد الصمد بن أحمد الشميهني يروي عن القاضي أبي بكر أحمد بن محمد بن إبراهيم الصدفي روى عنه أبو الفتح عبد الغافر بن الحسين الألمعي الحافظ وحدث عنه في معجم شيوخه |جـ 3 صـ 460| ",
                "title": "الشميهني",
                "uri": "JK_000952_2387"
            },
            "type": "Feature"
        }
    ],
    "type": "FeatureCollection"
}