{
    "features": [
        {
            "item": "JK_000952_2130",
            "properties": {
                "reference": "al-Samʿānī. <i>Kitāb al-ansāb</i>. (5 vols.) Bayrūt: Dār al-fikr, 1998, Vol.3, p.278",
                "source": "الأنساب للسمعاني",
                "text": "<h1>السلمي</h1> بفتح السين المهملة وسكون اللام هذه النسبة إلى الجد وهو ممن كان في آبائه وأجداده سلم منهم أبو إسحاق إبراهيم بن سلم بن محمد الشكاني السلمي قال أبو كامل البصيري يروي عنه فقيهنا طاهر بن الحسين الحريثي فيقول بالتدليس حدثنا أبو إسحاق السلمي لئلا يعرف أنه الشكاني قلت يروي عن ^ ^ وروى عنه السيد أبو بكر محمد بن علي بن حيدرة الجعفري وأبو الحسن علي بن محمد بن خدام البخاري وأبو خلف محمد بن عبد الملك بن خلف السلمي الطبري هكذا سمعت أبا عبد الله محمد بن الحسين الأزدي الحافظ يقول عن أستاذه أبي الفتح الموفق بن عبد الكريم الهروي وهو يروي عنه وسمع منه بغزنة وكان فقيها إماما فاضلا صنف مجموعا حسنا في المذهب لنا يقال له الكفاية لأبي خلف الطبري استحسنه كل من رآه وكانت وفاته في حدود سنة سبعين وأربعمائة ",
                "title": "السلمي",
                "uri": "JK_000952_2130"
            },
            "type": "Feature"
        }
    ],
    "type": "FeatureCollection"
}