{
    "features": [
        {
            "item": "JK_000129_001333",
            "properties": {
                "reference": "Yāqūt al-Ḥamawī. <i>Muʿjam al-buldān</i>. (5 vols.) Bayrūt: Dār Ṣādir, 1977, Vol.1, p.319",
                "source": "معجم البلدان لياقوت",
                "text": "<h1>بار والنسبة الباري</h1> من قرى نيسابور ينسب إليها الحسن بن نصر النيسابوري أبو علي الباري حدث عن الفضل بن أحمد الرازي حدث عنه أبو بكر بن أبي الحسين الحيري ومات بعد سنة 033 و سوق البار بلد باليمن بين صعدة وعثر وهو على التحديد بين الخصوف والمينا وقيل البار بلد قبلي توراب وشرقيها شامي يسكنه بنو رازح من خولان قضاعة وقال الأمير أبو نصر بن ماكولا عبد الله بن محمد بن حباب بن الهيثم بن محمد بن الربيع ابن خالد بن سعدان يعرف بالباري وليس من بار نيسابور وهو قرابة قحطبة بن شبيب ",
                "title": "بار والنسبة الباري",
                "uri": "JK_000129_001333"
            },
            "type": "Feature"
        }
    ],
    "type": "FeatureCollection"
}