{
    "features": [
        {
            "item": "JK_000129_005367",
            "properties": {
                "reference": "Yāqūt al-Ḥamawī. <i>Muʿjam al-buldān</i>. (5 vols.) Bayrūt: Dār Ṣādir, 1977, Vol.2, p.492",
                "source": "معجم البلدان لياقوت",
                "text": "<h1>دهلك</h1> بفتح أوله وسكون ثانيه ولام مفتوحة وآخره كاف اسم أعجمي معرب ويقال له دهيك أيضا وهي جزيرة في بحر اليمن وهو مرسى بين بلاد اليمن والحبشة بلدة ضيقة حرجة حارة كان بنو أمية إذا سخطوا على أحد نفوه إليها وقال أبو المقدام ولو أصبحت بنت القطامي دونها جبال بها الأكراد صم صخورها لباشرت ثوب الخوف حتى أزورها بنفسي إذا كانت بأرض تزورها ولو أصبحت خلف الثريا لزرتها بنفسي ولو كانت بدهلك دورها وقال أبو الفتح نصر الله بن عبد الله بن قلاقس الإسكندري يذكر دهلك وصاحبه مالك بن الشداد وأقبح بدهلك من بلدة فكل امرىء حلها هالك كفاك دليلا على أنها جحيم وخازنها مالك ",
                "title": "دهلك",
                "uri": "JK_000129_005367"
            },
            "type": "Feature"
        }
    ],
    "type": "FeatureCollection"
}