{
    "features": [
        {
            "item": "JK_000129_007754",
            "properties": {
                "reference": "Yāqūt al-Ḥamawī. <i>Muʿjam al-buldān</i>. (5 vols.) Bayrūt: Dār Ṣādir, 1977, Vol.3, pp.371-372",
                "source": "معجم البلدان لياقوت",
                "text": "<h1>شوزن</h1> بالزاي من مياه بني عقيل قاله أبو زياد الكلابي وأنشد للأعور بن براء ظلت على الشوزن الأعلى وأرقها برق بعردة أمثال المقابيس إن الأقمة من كتمان قد منعت جار ابن أخرم والمأنوس مأيوس |جـ 3 صـ 372| ",
                "title": "شوزن",
                "uri": "JK_000129_007754"
            },
            "type": "Feature"
        }
    ],
    "type": "FeatureCollection"
}