{
    "features": [
        {
            "item": "JK_000129_007655",
            "properties": {
                "reference": "Yāqūt al-Ḥamawī. <i>Muʿjam al-buldān</i>. (5 vols.) Bayrūt: Dār Ṣādir, 1977, Vol.3, p.360",
                "source": "معجم البلدان لياقوت",
                "text": "<h1>شلوبينية</h1> بفتح أوله وبعد الواو الساكنة باء موحدة مكسورة ثم ياء مثناة من تحت ونون مكسورة وياء أخرى خفيفة مثناة من تحت حصن بالأندلس من أعمال كورة إلبيرة على شاطىء البحر كثير الموز وقصب السكر والشاه بلوط ينسب إليها أبو علي عمر بن محمد بن عمر الأزدي النحوي إمام عظيم مقيم بإشبيلية وهو حي أو مات عن قريب أخبرني خبره أبو عبد الله محمد بن عبد الله المرسي يعرف بأبي الفضل وكان من تلاميذه ",
                "title": "شلوبينية",
                "uri": "JK_000129_007655"
            },
            "type": "Feature"
        }
    ],
    "type": "FeatureCollection"
}