{
    "features": [
        {
            "item": "JK_000952_2217",
            "properties": {
                "reference": "al-Samʿānī. <i>Kitāb al-ansāb</i>. (5 vols.) Bayrūt: Dār al-fikr, 1998, Vol.3, pp.339-340",
                "source": "الأنساب للسمعاني",
                "text": "<h1>السويقي</h1> بضم السين المهملة وفتح الواو وسكون الياء المنقوطة باثنتين من تحتها وفي آخرها القاف هذه النسبة إلى سويقة الصغد بالرزيق وهو موضع بمرو والسويقة تصغير السوق والمشهور بهذه النسبة أبو عمرو محمد بن أحمد بن محمد بن جميل السويقي المروزي يروي عن أبي داود سليمان بن الأشعث السجستاني |جـ 3 صـ 340| ",
                "title": "السويقي",
                "uri": "JK_000952_2217"
            },
            "type": "Feature"
        }
    ],
    "type": "FeatureCollection"
}