{
    "features": [
        {
            "item": "JK_000952_1306",
            "properties": {
                "reference": "al-Samʿānī. <i>Kitāb al-ansāb</i>. (5 vols.) Bayrūt: Dār al-fikr, 1998, Vol.2, p.315",
                "source": "الأنساب للسمعاني",
                "text": "<h1>الخاوسي</h1> بفتح الخاء المعجمة والواو وفي آخرها السين المهملة هذه النسبة إلى خاوس وهي من أعمال أسروشنة إحدى بلاد المشرق بين النهرين جيحون وسيحون خرج منها جماعة من العلماء والزهاد وفي الوقت الذي كنت بسمرقند كان بها فقيه يقال له الزاهد الخاوسي وكان يأمر بالمعروف وينهي عن المنكر ويضرب الناس على ذلك وأبو أحمد الزاهد السمرقندي الذي بنى الرباط في قرية قطوان وهو إليه ينسب بعده على سبعة فراسخ من سمرقند وقيل إن اسمه موسى يحكي عن أبي مقاتل حفص بن سلم الفزاري واجتمع مع شقيق بن إبراهيم البلخي حكى عنه أبو حفص عمر بن أحمد السمرقندي ويقال إن أصله كان بخارا ومات بخاوس من عمل أسروشنة منصرفة من الغزو فقبر ببورنمذ وهي من عمل سمرقند على اثني فرسخا منها قاله أبو سعد الإدريسي الحافظ ",
                "title": "الخاوسي",
                "uri": "JK_000952_1306"
            },
            "type": "Feature"
        }
    ],
    "type": "FeatureCollection"
}