{
    "features": [
        {
            "item": "JK_000129_004236",
            "properties": {
                "reference": "Yāqūt al-Ḥamawī. <i>Muʿjam al-buldān</i>. (5 vols.) Bayrūt: Dār Ṣādir, 1977, Vol.2, pp.306-307",
                "source": "معجم البلدان لياقوت",
                "text": "<h1>حمير والنسبة الحميري</h1> بالكسر ثم السكون وياء مفتوحة وراء قال ابن أبي الدمنة الهمذاني حمير بن الغوث بن سعد |جـ 2 صـ 307| ابن عوف بن عدي بن مالك بن زيد بن سدد بن حمير بن سبأ الأصغر بن لهيعة بن حمير بن سبأ بن يشجب وهو حمير الأكبر وحمير الغوث هو حمير الأدنى ومنازلهم باليمن بموضع يقال له حمير غربي صنعاء وهم أهل غتمة ولكنة في الكلام الحميري قال ولذلك يقول أهل صنعاء إذا أرادوا غتميا من أغتام بادية صنعاء هو حميري يريدون من حمير بن الغوث ولا يريدون حمير الأكبر ولا حمير بن سبأ الأصغر وهم يعلمون أن فيهم الفصاحة والشعر وإلى حمير بن الغوث هذا ينسب أكثر هذه اللغة الحميرية ",
                "title": "حمير والنسبة الحميري",
                "uri": "JK_000129_004236"
            },
            "type": "Feature"
        }
    ],
    "type": "FeatureCollection"
}