{
    "features": [
        {
            "item": "JK_000129_002897",
            "properties": {
                "reference": "Yāqūt al-Ḥamawī. <i>Muʿjam al-buldān</i>. (5 vols.) Bayrūt: Dār Ṣādir, 1977, Vol.2, p.84",
                "source": "معجم البلدان لياقوت",
                "text": "<h1>ثمانين والنسبة الثمانيني</h1> بلفظ العقد بين السبعين من العدد بليدة عند جبل الجودي قرب جزيرة ابن عمر التغلبي فوق الموصل كان أول من نزله نوح عليه السلام لما خرج من السفينة ومعه ثمانون إنسانا فبنوا لهم مساكن بهذا الموضع وأقاموا به فسمي الموضع بهم ثم أصابهم وباء فمات الثمانون غير نوح عليه السلام وولده فهو أبو البشر كلهم ومنها كان عمر بن ثابت الضريري الثمانيني صاحب التصانيف يكنى أبا القاسم أخذ عن ابن جني ومات في سنة 284 وعمر بن الخضر بن محمد أبو حفص يعرف بالثمانيني سمع بدمشق القاسم بن الفرج بن إبراهيم النصيبيني وبمصر أبا محمد الحسن بن رشيق روى عنه أبو عبد الله الأهوازي وأبو الحسن علي بن محمد بن شجاع المالكي ",
                "title": "ثمانين والنسبة الثمانيني",
                "uri": "JK_000129_002897"
            },
            "type": "Feature"
        }
    ],
    "type": "FeatureCollection"
}